maybedata.py
maybedata-0.8.dist-info/LICENSE
maybedata-0.8.dist-info/WHEEL
maybedata-0.8.dist-info/METADATA
maybedata-0.8.dist-info/RECORD
